{
    "type": "FeatureCollection",
    "features": [
        {
            "type": "Feature",
            "properties": {
                "name": "Torre della Garisenda",
                "ID": "BO_1"
            },
            "geometry": {
                "coordinates": [
                    11.3467,
                    44.4943
                ],
                "type": "Point"
            }
        },
        {
            "type": "Feature",
            "properties": {
                "name": "Basilica di San Domenico",
                "ID": "BO_2"
            },
            "geometry": {
                "coordinates": [
                    11.3439,
                    44.4895
                ],
                "type": "Point"
            },
            "id": 1
        },
        {
            "type": "Feature",
            "properties": {
                "name": "Ex Convento dei Frati Gaudenti",
                "ID": "BO_3"
            },
            "geometry": {
                "coordinates": [
                    11.3456754860361,
                    44.48739133587901
                ],
                "type": "Point"
            },
            "id": 2
        }
    ]
}